{
  "algo": "random",
  "track": "multi",
  "seed": 44,
  "budget": 50,
  "total_evaluated": 50,
  "pareto_size": 3,
  "hypervolume": 1.6834773125930717e+24,
  "hv_reference_point": [
    50701286.6956632,
    21022662.4757832,
    2579586847.746608
  ],
  "wall_time_s": 141.8727343082428,
  "started_at": "2026-04-08T08:36:10.203959+00:00",
  "finished_at": "2026-04-08T08:38:32.076710+00:00",
  "run_config": {
    "nn": "vgg8",
    "weights_path": "/Users/bytedance/workspace/MNSIM-2.0/cifar10_vgg8_params.pth",
    "base_config_path": "/Users/bytedance/workspace/MNSIM-2.0/SimConfig.ini",
    "run_accuracy": false,
    "device": "cpu",
    "algo_kwargs": {}
  },
  "best_by_objective": {
    "latency_ns": {
      "value": 3688343.5678964313,
      "eval_index": 38,
      "config": {
        "xbar_size": "256x256",
        "adc_choice": "7",
        "dac_choice": "3",
        "pe_num": "2x2",
        "tile_connection": "2",
        "inter_tile_bw": "80",
        "intra_tile_bw": "1024"
      }
    },
    "energy_nj": {
      "value": 431721.2155879321,
      "eval_index": 47,
      "config": {
        "xbar_size": "512x512",
        "adc_choice": "8",
        "dac_choice": "3",
        "pe_num": "2x2",
        "tile_connection": "1",
        "inter_tile_bw": "20",
        "intra_tile_bw": "1024"
      }
    },
    "area_um2": {
      "value": 832873846.2285514,
      "eval_index": 47,
      "config": {
        "xbar_size": "512x512",
        "adc_choice": "8",
        "dac_choice": "3",
        "pe_num": "2x2",
        "tile_connection": "1",
        "inter_tile_bw": "20",
        "intra_tile_bw": "1024"
      }
    }
  },
  "single_track_best": null
}